{
  "Version": 1,
  "WorkspaceRootPath": "C:\\Users\\valis\\source\\repos\\Clase 1 Python\\",
  "Documents": [
    {
      "AbsoluteMoniker": "D:0:0:{D3B65102-465A-4089-9822-0A3FAE9456EC}|Clase 1 Python.csproj|c:\\users\\valis\\source\\repos\\clase 1 python\\program.cs||{A6C744A8-0E4A-4FC6-886A-064283054674}",
      "RelativeMoniker": "D:0:0:{D3B65102-465A-4089-9822-0A3FAE9456EC}|Clase 1 Python.csproj|solutionrelative:program.cs||{A6C744A8-0E4A-4FC6-886A-064283054674}"
    }
  ],
  "DocumentGroupContainers": [
    {
      "Orientation": 0,
      "VerticalTabListWidth": 256,
      "DocumentGroups": [
        {
          "DockedWidth": 200,
          "SelectedChildIndex": 0,
          "Children": [
            {
              "$type": "Document",
              "DocumentIndex": 0,
              "Title": "Program.cs",
              "DocumentMoniker": "C:\\Users\\valis\\source\\repos\\Clase 1 Python\\Program.cs",
              "RelativeDocumentMoniker": "Program.cs",
              "ToolTip": "C:\\Users\\valis\\source\\repos\\Clase 1 Python\\Program.cs",
              "RelativeToolTip": "Program.cs",
              "ViewState": "AQIAAAAAAAAAAAAAAAAAAAAAAAAAAAAA",
              "Icon": "ae27a6b0-e345-4288-96df-5eaf394ee369.000738|",
              "WhenOpened": "2024-05-10T03:07:13.188Z",
              "EditorCaption": ""
            },
            {
              "$type": "Bookmark",
              "Name": "ST:0:0:{cce594b6-0c39-4442-ba28-10c64ac7e89f}"
            }
          ]
        }
      ]
    }
  ]
}